audit_logger/__init__.py
audit_logger/apps.py
audit_logger/logger.py
audit_logger/middlewares.py
audit_logger/producer.py
django_audit_kafkalogger-0.2.dist-info/LICENSE
django_audit_kafkalogger-0.2.dist-info/METADATA
django_audit_kafkalogger-0.2.dist-info/WHEEL
django_audit_kafkalogger-0.2.dist-info/top_level.txt
django_audit_kafkalogger-0.2.dist-info/RECORD
