Metadata-Version: 2.1
Name: django-audit-kafkalogger
Version: 0.2
Summary: A reusable Django app for auditing models automatically with Kafka integration
Home-page: https://github.com/marcosdaniel2002/django-audit-kafkalogger
Author: Marcos Daniel
Author-email: mteranc@unemi.edu.ec
License: MIT
Classifier: Framework :: Django
Classifier: Programming Language :: Python
Classifier: Programming Language :: Python :: 3
Classifier: License :: OSI Approved :: MIT License
Classifier: Operating System :: OS Independent
Requires-Python: >=3.6
License-File: LICENSE
Requires-Dist: Django >=3.0
Requires-Dist: confluent-kafka >=1.7.0
